reze/__init__.py
reze/api_client.py
reze/api_requests/__init__.py
reze/api_requests/salebot_add_interaction.py
reze/api_requests/salebot_bought_together.py
reze/api_requests/salebot_items_to_item.py
reze-0.2.dist-info/METADATA
reze-0.2.dist-info/WHEEL
reze-0.2.dist-info/top_level.txt
reze-0.2.dist-info/RECORD
